pseudobatch/__init__.py
pseudobatch/data_correction.py
pseudobatch/import_from_excel.py
pseudobatch/util.py
pseudobatch/datasets/__init__.py
pseudobatch/datasets/_dataloaders.py
pseudobatch/datasets/data/biolector_yeast_fedbatch.csv
pseudobatch/datasets/data/evaporation.csv
pseudobatch/datasets/data/multiple_impulse_feed_process.csv
pseudobatch/datasets/data/product_inhibition.csv
pseudobatch/datasets/data/standard_fed-batch_process.csv
pseudobatch/datasets/data/volatile_product.csv
pseudobatch/error_propagation/__init__.py
pseudobatch/error_propagation/error_propagation.py
pseudobatch/error_propagation/stan/__init__.py
pseudobatch/error_propagation/stan/error_propagation.stan
pseudobatch/error_propagation/stan/functions.stan
pseudobatch-1.0.1.dist-info/LICENSE
pseudobatch-1.0.1.dist-info/METADATA
pseudobatch-1.0.1.dist-info/WHEEL
pseudobatch-1.0.1.dist-info/top_level.txt
pseudobatch-1.0.1.dist-info/RECORD
