Metadata-Version: 2.2
Name: pseudobatch
Version: 1.0.1
Summary: Transform data from fed batch cultures to get equivalent batch culture values
Home-page: https://github.com/viktorht/pseudobatch
Author: Viktor Hesselberg-Thomsen and Teddy Groves
Author-email: vikhes@biosustain.dtu.dk
License: MIT license
License-File: LICENSE
Requires-Dist: numpy
Requires-Dist: pandas
Provides-Extra: development
Requires-Dist: flake8; extra == "development"
Requires-Dist: pytest; extra == "development"
Requires-Dist: mypy; extra == "development"
Requires-Dist: isort; extra == "development"
Requires-Dist: black; extra == "development"
Requires-Dist: patsy; extra == "development"
Requires-Dist: statsmodels; extra == "development"
Provides-Extra: documentation
Requires-Dist: sphinx; extra == "documentation"
Requires-Dist: nbsphinx; extra == "documentation"
Requires-Dist: pydata-sphinx-theme; extra == "documentation"
Provides-Extra: error-propagation
Requires-Dist: arviz; extra == "error-propagation"
Requires-Dist: cmdstanpy>=1.0.7; extra == "error-propagation"
Requires-Dist: pydantic==2.4.2; extra == "error-propagation"
